whiteduck/__init__.py
whiteduck/templates/cli/README.md
whiteduck/templates/cli/pyproject.toml
whiteduck/templates/cli/.vscode/launch.json
whiteduck/templates/cli/.vscode/settings.json
whiteduck/templates/cli/.vscode/tasks.json
whiteduck/templates/cli/src/myproject/__init__.py
whiteduck/templates/cli/tests/test_myproject.py
whiteduck/templates/lib/README.md
whiteduck/templates/lib/pyproject.toml
whiteduck/templates/lib/.vscode/launch.json
whiteduck/templates/lib/.vscode/settings.json
whiteduck/templates/lib/.vscode/tasks.json
whiteduck/templates/lib/src/myproject/my_model.py
whiteduck/templates/lib/tests/test_myproject.py
whiteduck/templates/llm/.env.example
whiteduck/templates/llm/.gitignore
whiteduck/templates/llm/.python-version
whiteduck/templates/llm/README.md
whiteduck/templates/llm/chainlit.md
whiteduck/templates/llm/pyproject.toml
whiteduck/templates/llm/.chainlit/config.toml
whiteduck/templates/llm/.chainlit/translations/bn.json
whiteduck/templates/llm/.chainlit/translations/en-US.json
whiteduck/templates/llm/.chainlit/translations/gu.json
whiteduck/templates/llm/.chainlit/translations/he-IL.json
whiteduck/templates/llm/.chainlit/translations/hi.json
whiteduck/templates/llm/.chainlit/translations/kn.json
whiteduck/templates/llm/.chainlit/translations/ml.json
whiteduck/templates/llm/.chainlit/translations/mr.json
whiteduck/templates/llm/.chainlit/translations/ta.json
whiteduck/templates/llm/.chainlit/translations/te.json
whiteduck/templates/llm/.chainlit/translations/zh-CN.json
whiteduck/templates/llm/.vscode/launch.json
whiteduck/templates/llm/.vscode/settings.json
whiteduck/templates/llm/.vscode/tasks.json
whiteduck/templates/llm/src/myproject/__init__.py
whiteduck/templates/llm/src/myproject/config.py
whiteduck/templates/react/.gitignore
whiteduck/templates/react/.python-version
whiteduck/templates/react/README.md
whiteduck/templates/react/pyproject.toml
whiteduck/templates/react/.vscode/launch.json
whiteduck/templates/react/.vscode/settings.json
whiteduck-0.5.0.dist-info/METADATA
whiteduck-0.5.0.dist-info/WHEEL
whiteduck-0.5.0.dist-info/entry_points.txt
whiteduck-0.5.0.dist-info/RECORD
