Metadata-Version: 2.3
Name: whiteduck
Version: 0.5.0
Summary: Add your description here
Author-email: Andre Ratzenberger <andre.ratzenberger@whiteduck.de>
Requires-Python: >=3.10
Requires-Dist: rich>=13.9.4
Requires-Dist: typer>=0.15.1
